{
  "generated_at": "2026-07-09T01:13:14.000417",
  "results": [
    {
      "success": false,
      "error": "Failed after retries",
      "keyword": "modern office workspace",
      "category": "business"
    },
    {
      "success": false,
      "error": "Failed after retries",
      "keyword": "professional business meeting",
      "category": "business"
    },
    {
      "success": false,
      "error": "Failed after retries",
      "keyword": "startup team collaboration",
      "category": "business"
    },
    {
      "success": false,
      "error": "Failed after retries",
      "keyword": "corporate executive portrait",
      "category": "business"
    },
    {
      "success": false,
      "error": "Failed after retries",
      "keyword": "mountain landscape sunset",
      "category": "nature"
    },
    {
      "success": false,
      "error": "Failed after retries",
      "keyword": "ocean beach waves",
      "category": "nature"
    },
    {
      "success": false,
      "error": "Failed after retries",
      "keyword": "forest trees sunlight",
      "category": "nature"
    },
    {
      "success": false,
      "error": "Failed after retries",
      "keyword": "flower garden spring",
      "category": "nature"
    },
    {
      "success": false,
      "error": "Failed after retries",
      "keyword": "artificial intelligence technology",
      "category": "technology"
    },
    {
      "success": false,
      "error": "Failed after retries",
      "keyword": "computer coding workspace",
      "category": "technology"
    },
    {
      "success": false,
      "error": "Failed after retries",
      "keyword": "smartphone mobile app",
      "category": "technology"
    },
    {
      "success": false,
      "error": "Failed after retries",
      "keyword": "data visualization charts",
      "category": "technology"
    },
    {
      "success": false,
      "error": "Failed after retries",
      "keyword": "healthy food salad bowl",
      "category": "food"
    },
    {
      "success": false,
      "error": "Failed after retries",
      "keyword": "coffee cup cafe",
      "category": "food"
    },
    {
      "success": false,
      "error": "Failed after retries",
      "keyword": "restaurant dining table",
      "category": "food"
    },
    {
      "success": false,
      "error": "Failed after retries",
      "keyword": "diverse people group",
      "category": "people"
    },
    {
      "success": false,
      "error": "Failed after retries",
      "keyword": "happy family moment",
      "category": "people"
    },
    {
      "success": false,
      "error": "Failed after retries",
      "keyword": "fitness yoga exercise",
      "category": "health"
    },
    {
      "success": false,
      "error": "Failed after retries",
      "keyword": "abstract geometric pattern",
      "category": "abstract"
    },
    {
      "success": false,
      "error": "Failed after retries",
      "keyword": "city skyline architecture",
      "category": "travel"
    }
  ]
}